simple_jinjamator/__init__.py
simple_jinjamator/rest_client/LICENSE
simple_jinjamator/rest_client/README
simple_jinjamator/rest_client/__init__.py
simple_jinjamator/rest_client/api.py
simple_jinjamator/rest_client/curlify.py
simple_jinjamator/rest_client/decorators.py
simple_jinjamator/rest_client/exceptions.py
simple_jinjamator/rest_client/models.py
simple_jinjamator/rest_client/request.py
simple_jinjamator/rest_client/resource.py
simple_jinjamator-0.1.1.dist-info/LICENSE
simple_jinjamator-0.1.1.dist-info/METADATA
simple_jinjamator-0.1.1.dist-info/WHEEL
simple_jinjamator-0.1.1.dist-info/top_level.txt
simple_jinjamator-0.1.1.dist-info/RECORD
