Metadata-Version: 2.1
Name: simple-jinjamator
Version: 0.1.1
Summary: Simple REST-client for jinjamator
Home-page: https://github.com/jinjamator/simple_jinjamator
Author: Wilhelm Putz
Author-email: wilhelm.putz@cancom.com
License: ASL V2
Platform: UNKNOWN
Classifier: License :: OSI Approved :: Apache Software License
Classifier: Programming Language :: Python :: 3.7
Classifier: Programming Language :: Python :: 3.8
Classifier: Topic :: System :: Installation/Setup
Classifier: Topic :: System :: Systems Administration
Classifier: Topic :: Utilities
Requires-Python: >=3.7
License-File: LICENSE
Requires-Dist: httpx
Requires-Dist: python-status
